{
  "id": "seed01",
  "name": "01 · Semilla de demostración — Torre de Control",
  "nodes": [
    {
      "parameters": {},
      "id": "42f0d9c7-7d99-4d70-912e-123456789001",
      "name": "Al ejecutar manualmente",
      "type": "n8n-nodes-base.manualTrigger",
      "typeVersion": 1,
      "position": [240, 300]
    },
    {
      "parameters": {
        "jsCode": "// Este nodo es la fuente de verdad temporal del laboratorio.\n// Reemplázalo por conectores reales en el workflow 02.\nconst capturedAt = new Date().toISOString();\nconst projects = [\n  { id: 'PROY-01', name: 'Portal de aliados', owner: 'Lucía', status: 'en_riesgo', priority: 'alta', due: '2026-07-24', progress: 62, blocker: 'Falta decisión de Legal sobre términos.' },\n  { id: 'PROY-02', name: 'Onboarding comercial', owner: 'Miguel', status: 'en_curso', priority: 'media', due: '2026-08-02', progress: 48, blocker: '' },\n  { id: 'PROY-03', name: 'Migración CRM', owner: 'Sara', status: 'bloqueado', priority: 'critica', due: '2026-07-22', progress: 31, blocker: 'Proveedor no entregó acceso a la API.' }\n];\nconst events = [\n  { id: 'EVT-01', title: 'Comité de lanzamiento', start: '2026-07-21T09:00:00-05:00', projectId: 'PROY-01', type: 'decision' },\n  { id: 'EVT-02', title: 'Demo de onboarding', start: '2026-07-23T15:00:00-05:00', projectId: 'PROY-02', type: 'milestone' },\n  { id: 'EVT-03', title: 'Escalamiento con proveedor', start: '2026-07-20T16:30:00-05:00', projectId: 'PROY-03', type: 'blocker' }\n];\nconst milestones = [\n  { id: 'HIT-01', projectId: 'PROY-01', title: 'Aprobación de términos', date: '2026-07-21', status: 'at_risk' },\n  { id: 'HIT-02', projectId: 'PROY-02', title: 'Piloto con ventas', date: '2026-07-26', status: 'on_track' },\n  { id: 'HIT-03', projectId: 'PROY-03', title: 'Acceso a API CRM', date: '2026-07-20', status: 'blocked' }\n];\nreturn [{ json: { capturedAt, projects, events, milestones } }];"
      },
      "id": "42f0d9c7-7d99-4d70-912e-123456789002",
      "name": "Semilla: tres fuentes",
      "type": "n8n-nodes-base.code",
      "typeVersion": 2,
      "position": [460, 300]
    },
    {
      "parameters": {
        "jsCode": "const data = $input.first().json;\nconst byProject = new Map(data.projects.map((project) => [project.id, { ...project, events: [], milestones: [] }]));\nfor (const event of data.events) byProject.get(event.projectId)?.events.push(event);\nfor (const milestone of data.milestones) byProject.get(milestone.projectId)?.milestones.push(milestone);\nconst projects = [...byProject.values()];\nconst summary = {\n  totalProjects: projects.length,\n  blocked: projects.filter((p) => p.status === 'bloqueado').length,\n  atRisk: projects.filter((p) => p.status === 'en_riesgo').length,\n  decisionsNeeded: projects.filter((p) => p.blocker).map((p) => ({ project: p.name, owner: p.owner, request: p.blocker })),\n  nextEvents: data.events.slice().sort((a, b) => a.start.localeCompare(b.start)).slice(0, 3)\n};\nreturn [{ json: { generatedAt: data.capturedAt, summary, projects } }];"
      },
      "id": "42f0d9c7-7d99-4d70-912e-123456789003",
      "name": "Normalizar y priorizar",
      "type": "n8n-nodes-base.code",
      "typeVersion": 2,
      "position": [700, 300]
    },
    {
      "parameters": { "content": "CÓMO VER EL RESULTADO\n\nEste recuadro es una nota del lienzo: no recibe datos ni evalúa expresiones (un sticky note nunca se ejecuta, y por eso ni siquiera aparece conectado a otros nodos). Aquí NO vas a ver el snapshot.\n\nPara ver el resultado real:\n\n1. Haz clic en el nodo \"Normalizar y priorizar\".\n2. Abre la pestaña de salida (Output) en el panel derecho.\n3. Ahí está el JSON procesado: resumen, decisiones pendientes y los tres proyectos con sus eventos e hitos.\n\nCambia un dato en \"Semilla: tres fuentes\" (por ejemplo, pon un status en 'bloqueado') y vuelve a ejecutar. Ese panel de salida es donde vas a ver el cambio — identifica qué regla del nodo \"Normalizar y priorizar\" lo produjo.", "height": 400, "width": 460, "color": 6 },
      "id": "42f0d9c7-7d99-4d70-912e-123456789004",
      "name": "Nota: cómo ver el resultado",
      "type": "n8n-nodes-base.stickyNote",
      "typeVersion": 1,
      "position": [940, 150]
    },
    {
      "parameters": { "content": "RELACIÓN CON EL WORKFLOW 03\n\nEste workflow (01) muestra la NORMALIZACIÓN: toma tres fuentes crudas y las convierte en un snapshot único con prioridades.\n\nEl workflow \"03 · Informe ejecutivo\" parte de los MISMOS datos (Portal de aliados/Lucía/en_riesgo, Onboarding comercial/Miguel/en_curso, Migración CRM/Sara/bloqueado) y los redacta como informe para un director.\n\nSon independientes: cada uno se importa y se ejecuta por separado. Juntos enseñan dos etapas de la misma torre de control.", "height": 260, "width": 460, "color": 3 },
      "id": "42f0d9c7-7d99-4d70-912e-123456789005",
      "name": "Nota: relación con el workflow 03",
      "type": "n8n-nodes-base.stickyNote",
      "typeVersion": 1,
      "position": [940, 580]
    }
  ],
  "pinData": {},
  "connections": {
    "Al ejecutar manualmente": { "main": [[{ "node": "Semilla: tres fuentes", "type": "main", "index": 0 }]] },
    "Semilla: tres fuentes": { "main": [[{ "node": "Normalizar y priorizar", "type": "main", "index": 0 }]] }
  },
  "active": false,
  "settings": { "executionOrder": "v1" },
  "versionId": "42f0d9c7-7d99-4d70-912e-123456789001",
  "meta": { "templateCredsSetupCompleted": false },
  "tags": []
}
